hurray/__init__.py
hurray-1.1.1.dist-info/LICENSE
hurray-1.1.1.dist-info/METADATA
hurray-1.1.1.dist-info/WHEEL
hurray-1.1.1.dist-info/top_level.txt
hurray-1.1.1.dist-info/RECORD
