Metadata-Version: 2.1
Name: hurray
Version: 1.1.1
Summary: Simple collection of wrappers around Python's builtin 'array' module
Author: SyberiaK, trag1c, CircuitSacul, Micael Jarniac, bswck
License: MIT License
Project-URL: Homepage, https://github.com/SyberiaK/hurray
Project-URL: Issues, https://github.com/SyberiaK/hurray/issues
Classifier: Development Status :: 6 - Mature
Classifier: Intended Audience :: Developers
Classifier: License :: OSI Approved :: MIT License
Classifier: Operating System :: OS Independent
Classifier: Programming Language :: Python :: 3.8
Classifier: Programming Language :: Python :: 3.9
Classifier: Programming Language :: Python :: 3.10
Classifier: Programming Language :: Python :: 3.11
Classifier: Programming Language :: Python :: 3.12
Classifier: Programming Language :: Python :: 3.13
Classifier: Topic :: Utilities
Classifier: Typing :: Typed
Requires-Python: >=3.8
License-File: LICENSE
